{"nodes": [{"id": "d_project_atlas_specify_specs_sys_ui_spec_md", "label": "sys_ui.spec.md", "file_type": "document", "source_file": ".specify/specs/sys_ui.spec.md", "source_location": "L1"}, {"id": "specs_sys_ui_spec_feature_specification_ui_ux_portal_screens_sys_ui", "label": "Feature Specification: UI/UX & Portal Screens (SYS-UI)", "file_type": "document", "source_file": ".specify/specs/sys_ui.spec.md", "source_location": "L1"}, {"id": "specs_sys_ui_spec_1_overview_goal", "label": "1. Overview & Goal", "file_type": "document", "source_file": ".specify/specs/sys_ui.spec.md", "source_location": "L3"}, {"id": "specs_sys_ui_spec_2_design_tokens_styles", "label": "2. Design Tokens & Styles", "file_type": "document", "source_file": ".specify/specs/sys_ui.spec.md", "source_location": "L8"}, {"id": "specs_sys_ui_spec_3_screen_specifications_5_mvp_screens", "label": "3. Screen Specifications (5 MVP Screens)", "file_type": "document", "source_file": ".specify/specs/sys_ui.spec.md", "source_location": "L18"}, {"id": "specs_sys_ui_spec_a_dashboard_dashboard", "label": "A. Dashboard (`/dashboard`)", "file_type": "document", "source_file": ".specify/specs/sys_ui.spec.md", "source_location": "L20"}, {"id": "specs_sys_ui_spec_b_knowledge_graph_explorer_graph", "label": "B. Knowledge Graph Explorer (`/graph`)", "file_type": "document", "source_file": ".specify/specs/sys_ui.spec.md", "source_location": "L25"}, {"id": "specs_sys_ui_spec_c_research_workspace_research", "label": "C. Research Workspace (`/research`)", "file_type": "document", "source_file": ".specify/specs/sys_ui.spec.md", "source_location": "L29"}, {"id": "specs_sys_ui_spec_d_content_factory_factory", "label": "D. Content Factory (`/factory`)", "file_type": "document", "source_file": ".specify/specs/sys_ui.spec.md", "source_location": "L33"}, {"id": "specs_sys_ui_spec_e_analytics_dashboard_analytics", "label": "E. Analytics Dashboard (`/analytics`)", "file_type": "document", "source_file": ".specify/specs/sys_ui.spec.md", "source_location": "L38"}, {"id": "specs_sys_ui_spec_4_edge_cases", "label": "4. Edge Cases", "file_type": "document", "source_file": ".specify/specs/sys_ui.spec.md", "source_location": "L44"}], "edges": [{"source": "d_project_atlas_specify_specs_sys_ui_spec_md", "target": "specs_sys_ui_spec_feature_specification_ui_ux_portal_screens_sys_ui", "relation": "contains", "confidence": "EXTRACTED", "source_file": ".specify/specs/sys_ui.spec.md", "source_location": "L1", "weight": 1.0}, {"source": "specs_sys_ui_spec_feature_specification_ui_ux_portal_screens_sys_ui", "target": "specs_sys_ui_spec_1_overview_goal", "relation": "contains", "confidence": "EXTRACTED", "source_file": ".specify/specs/sys_ui.spec.md", "source_location": "L3", "weight": 1.0}, {"source": "specs_sys_ui_spec_feature_specification_ui_ux_portal_screens_sys_ui", "target": "specs_sys_ui_spec_2_design_tokens_styles", "relation": "contains", "confidence": "EXTRACTED", "source_file": ".specify/specs/sys_ui.spec.md", "source_location": "L8", "weight": 1.0}, {"source": "specs_sys_ui_spec_feature_specification_ui_ux_portal_screens_sys_ui", "target": "specs_sys_ui_spec_3_screen_specifications_5_mvp_screens", "relation": "contains", "confidence": "EXTRACTED", "source_file": ".specify/specs/sys_ui.spec.md", "source_location": "L18", "weight": 1.0}, {"source": "specs_sys_ui_spec_3_screen_specifications_5_mvp_screens", "target": "specs_sys_ui_spec_a_dashboard_dashboard", "relation": "contains", "confidence": "EXTRACTED", "source_file": ".specify/specs/sys_ui.spec.md", "source_location": "L20", "weight": 1.0}, {"source": "specs_sys_ui_spec_3_screen_specifications_5_mvp_screens", "target": "specs_sys_ui_spec_b_knowledge_graph_explorer_graph", "relation": "contains", "confidence": "EXTRACTED", "source_file": ".specify/specs/sys_ui.spec.md", "source_location": "L25", "weight": 1.0}, {"source": "specs_sys_ui_spec_3_screen_specifications_5_mvp_screens", "target": "specs_sys_ui_spec_c_research_workspace_research", "relation": "contains", "confidence": "EXTRACTED", "source_file": ".specify/specs/sys_ui.spec.md", "source_location": "L29", "weight": 1.0}, {"source": "specs_sys_ui_spec_3_screen_specifications_5_mvp_screens", "target": "specs_sys_ui_spec_d_content_factory_factory", "relation": "contains", "confidence": "EXTRACTED", "source_file": ".specify/specs/sys_ui.spec.md", "source_location": "L33", "weight": 1.0}, {"source": "specs_sys_ui_spec_3_screen_specifications_5_mvp_screens", "target": "specs_sys_ui_spec_e_analytics_dashboard_analytics", "relation": "contains", "confidence": "EXTRACTED", "source_file": ".specify/specs/sys_ui.spec.md", "source_location": "L38", "weight": 1.0}, {"source": "specs_sys_ui_spec_feature_specification_ui_ux_portal_screens_sys_ui", "target": "specs_sys_ui_spec_4_edge_cases", "relation": "contains", "confidence": "EXTRACTED", "source_file": ".specify/specs/sys_ui.spec.md", "source_location": "L44", "weight": 1.0}], "input_tokens": 0, "output_tokens": 0}